kik_desktop/__init__.py
kik_desktop/app.py
kik_desktop/dark_theme.css
kik_desktop/kik_thread.py
kik_desktop/light_theme.css
kik_desktop/util.py
kik_desktop/ui/__init__.py
kik_desktop/ui/login_widget.py
kik_desktop/ui/main_widget.py
kik_desktop-0.0.2.dist-info/DESCRIPTION.rst
kik_desktop-0.0.2.dist-info/METADATA
kik_desktop-0.0.2.dist-info/RECORD
kik_desktop-0.0.2.dist-info/WHEEL
kik_desktop-0.0.2.dist-info/entry_points.txt
kik_desktop-0.0.2.dist-info/metadata.json
kik_desktop-0.0.2.dist-info/top_level.txt
