Metadata-Version: 2.0
Name: kik-desktop
Version: 0.0.2
Summary: Kik Desktop
Home-page: https://github.com/Jaapp-/kik-desktop
Author: Jaap Heijligers
Author-email: mail@heijligers.me
License: GPLv2
Keywords: kik desktop chat
Platform: UNKNOWN
Classifier: Development Status :: 3 - Alpha
Classifier: Programming Language :: Python :: 3
Classifier: Intended Audience :: End Users/Desktop
Classifier: License :: OSI Approved :: GNU General Public License v2 (GPLv2)
Classifier: Topic :: Communications :: Chat
Requires-Dist: PyQt5
Requires-Dist: appdirs
Requires-Dist: kik-unofficial
Provides-Extra: dev
Provides-Extra: test
